ble_library.py
ble_library-1.0.0.dist-info/METADATA
ble_library-1.0.0.dist-info/WHEEL
ble_library-1.0.0.dist-info/top_level.txt
ble_library-1.0.0.dist-info/RECORD
